vulcan_api_client/__init__.py
vulcan_api_client/core.py
vulcan_api_client-1.0.5.dist-info/METADATA
vulcan_api_client-1.0.5.dist-info/WHEEL
vulcan_api_client-1.0.5.dist-info/top_level.txt
vulcan_api_client-1.0.5.dist-info/RECORD
