Metadata-Version: 2.4
Name: vulcan-api-client
Version: 1.0.5
Summary: Full-featured Vulcan API
Author: Jake
Author-email: jakub201307@gmail.com
Requires-Dist: requests
Requires-Dist: selenium
Dynamic: author
Dynamic: author-email
Dynamic: requires-dist
Dynamic: summary
